pytest_testrail/__init__.py
pytest_testrail/conftest.py
pytest_testrail/plugin.py
pytest_testrail/testrail_api.py
testrail_pytest-1.0.0.dist-info/METADATA
testrail_pytest-1.0.0.dist-info/WHEEL
testrail_pytest-1.0.0.dist-info/entry_points.txt
testrail_pytest-1.0.0.dist-info/top_level.txt
testrail_pytest-1.0.0.dist-info/RECORD
