Metadata-Version: 2.1
Name: testrail-pytest
Version: 1.0.0
Summary: pytest plugin for creating TestRail runs and adding results
Home-page: http://github.com/II-VSB-II/pytest-testrail/
Author: Vivek Singh
Author-email: vs.bhadauriya@live.com
License: UNKNOWN
Platform: UNKNOWN
Requires-Dist: pytest (>=3.6)
Requires-Dist: requests (>=2.20.0)
